jldrpi
