Metadata-Version: 1.0
Name: jldrpi
Version: 0.2
Summary: Collection of Raspberry Pi related tools
Home-page: https://github.com/jldupont/jldrpi
Author: Jean-Lou Dupont
Author-email: jl@jldupont.com
License: UNKNOWN
Platform: UNKNOWN
